{"id":268,"status":"Fixed","summary":"resolveTypes: jstype.UnionType cannot be cast to jstype.ObjectType","labels":["Type-Defect","Priority-Medium"],"stars":1,"commentCount":4,"comments":[{"id":0,"commenterId":-1243799424994853444,"content":"\u003cb\u003eWhat steps will reproduce the problem?\u003c/b\u003e\n\r\n1. Compile a bunch of JavaScript files that I can\u0027t release with these options: [\u0027--create_name_map_files\u0027, \u0027true\u0027, \u0027--jscomp_warning\u0027, \u0027missingProperties\u0027, \u0027--jscomp_warning\u0027, \u0027undefinedVars\u0027, \u0027--jscomp_warning\u0027, \u0027checkTypes\u0027, \u0027--warning_level\u0027, \u0027VERBOSE\u0027, \u0027--summary_detail_level\u0027, \u00273\u0027, \u0027--process_closure_primitives\u0027, \u0027true\u0027, \u0027--jscomp_error\u0027, \u0027strictModuleDepCheck\u0027, \u0027--jscomp_error\u0027, \u0027invalidCasts\u0027, \u0027--logging_level\u0027, \u0027ALL\u0027, \u0027--compilation_level\u0027, \u0027ADVANCED_OPTIMIZATIONS\u0027]\r\n\r\n2. During this pass:\r\n\r\n        Oct 26, 2010 12:09:38 AM com.google.javascript.jscomp.PhaseOptimizer$NamedPass process\r\n        INFO: resolveTypes\r\n\r\n, compilation terminates with:\r\n\r\n        java.lang.RuntimeException: java.lang.ClassCastException: com.google.javascript.rhino.jstype.UnionType cannot be cast to com.google.javascript.rhino.jstype.ObjectType\r\n                at com.google.javascript.jscomp.Compiler.runInCompilerThread(Unknown Source)\r\n                at com.google.javascript.jscomp.Compiler.compile(Unknown Source)\r\n                at com.google.javascript.jscomp.Compiler.compile(Unknown Source)\r\n                at com.google.javascript.jscomp.AbstractCommandLineRunner.doRun(Unknown Source)\r\n                at com.google.javascript.jscomp.AbstractCommandLineRunner.run(Unknown Source)\r\n                at com.google.javascript.jscomp.CommandLineRunner.main(Unknown Source)\r\n        Caused by: java.lang.ClassCastException: com.google.javascript.rhino.jstype.UnionType cannot be cast to com.google.javascript.rhino.jstype.ObjectType\r\n                at com.google.javascript.rhino.jstype.FunctionType.resolveInternal(Unknown Source)\r\n                at com.google.javascript.rhino.jstype.JSType.resolve(Unknown Source)\r\n                at com.google.javascript.jscomp.TypedScopeCreator$DeferredSetType.resolve(Unknown Source)\r\n                at com.google.javascript.jscomp.TypedScopeCreator$AbstractScopeBuilder.resolveTypes(Unknown Source)\r\n                at com.google.javascript.jscomp.TypedScopeCreator.createScope(Unknown Source)\r\n                at com.google.javascript.jscomp.MemoizedScopeCreator.createScope(Unknown Source)\r\n                at com.google.javascript.jscomp.DefaultPassConfig$GlobalTypeResolver.process(Unknown Source)\r\n                at com.google.javascript.jscomp.PhaseOptimizer$PassFactoryDelegate.processInternal(Unknown Source)\r\n                at com.google.javascript.jscomp.PhaseOptimizer$NamedPass.process(Unknown Source)\r\n                at com.google.javascript.jscomp.PhaseOptimizer.process(Unknown Source)\r\n                at com.google.javascript.jscomp.Compiler.check(Unknown Source)\r\n                at com.google.javascript.jscomp.Compiler.compileInternal(Unknown Source)\r\n                at com.google.javascript.jscomp.Compiler.access$000(Unknown Source)\r\n                at com.google.javascript.jscomp.Compiler$1.call(Unknown Source)\r\n                at com.google.javascript.jscomp.Compiler$1.call(Unknown Source)\r\n                at com.google.javascript.jscomp.Compiler$2.run(Unknown Source)\r\n                at java.lang.Thread.run(Thread.java:662)\r\n\r\n\r\n\u003cb\u003eWhat version of the product are you using? On what operating system?\u003c/b\u003e\n\r\nI\u0027m using Closure Compiler r506.  The problem first appeared in r482.","timestamp":1288052183,"attachments":[]},{"id":1,"commenterId":-1243799424994853444,"content":"The traceback with line numbers:\r\n\r\n        java.lang.RuntimeException: java.lang.ClassCastException: com.google.javascript.rhino.jstype.UnionType cannot be cast to com.google.javascript.rhino.jstype.ObjectType\r\n                at com.google.javascript.jscomp.Compiler.runInCompilerThread(Compiler.java:590)\r\n                at com.google.javascript.jscomp.Compiler.compile(Compiler.java:528)\r\n                at com.google.javascript.jscomp.Compiler.compile(Compiler.java:487)\r\n                at com.google.javascript.jscomp.AbstractCommandLineRunner.doRun(AbstractCommandLineRunner.java:583)\r\n                at com.google.javascript.jscomp.AbstractCommandLineRunner.run(AbstractCommandLineRunner.java:252)\r\n                at com.google.javascript.jscomp.CommandLineRunner.main(CommandLineRunner.java:618)\r\n        Caused by: java.lang.ClassCastException: com.google.javascript.rhino.jstype.UnionType cannot be cast to com.google.javascript.rhino.jstype.ObjectType\r\n                at com.google.javascript.rhino.jstype.FunctionType.resolveInternal(FunctionType.java:856)\r\n                at com.google.javascript.rhino.jstype.JSType.resolve(JSType.java:894)\r\n                at com.google.javascript.jscomp.TypedScopeCreator$DeferredSetType.resolve(TypedScopeCreator.java:136)\r\n                at com.google.javascript.jscomp.TypedScopeCreator$AbstractScopeBuilder.resolveTypes(TypedScopeCreator.java:399)\r\n                at com.google.javascript.jscomp.TypedScopeCreator.createScope(TypedScopeCreator.java:178)\r\n                at com.google.javascript.jscomp.MemoizedScopeCreator.createScope(MemoizedScopeCreator.java:53)\r\n                at com.google.javascript.jscomp.DefaultPassConfig$GlobalTypeResolver.process(DefaultPassConfig.java:1053)\r\n                at com.google.javascript.jscomp.PhaseOptimizer$PassFactoryDelegate.processInternal(PhaseOptimizer.java:271)\r\n                at com.google.javascript.jscomp.PhaseOptimizer$NamedPass.process(PhaseOptimizer.java:248)\r\n                at com.google.javascript.jscomp.PhaseOptimizer.process(PhaseOptimizer.java:167)\r\n                at com.google.javascript.jscomp.Compiler.check(Compiler.java:694)\r\n                at com.google.javascript.jscomp.Compiler.compileInternal(Compiler.java:613)\r\n                at com.google.javascript.jscomp.Compiler.access$000(Compiler.java:64)\r\n                at com.google.javascript.jscomp.Compiler$1.call(Compiler.java:530)\r\n                at com.google.javascript.jscomp.Compiler$1.call(Compiler.java:528)\r\n                at com.google.javascript.jscomp.Compiler$2.run(Compiler.java:562)\r\n                at java.lang.Thread.run(Thread.java:662)","timestamp":1288052796,"attachments":[]},{"id":2,"commenterId":-7699928860083865744,"content":"thanks for the report!","timestamp":1288134330,"attachments":[]},{"id":3,"commenterId":-7699928860083865744,"content":"This issue was closed by revision r519.","timestamp":1288295819,"attachments":[]}]}