{"id":190,"status":"Fixed","summary":"Bug with labeled loops and breaks","labels":["Type-Defect","Priority-High"],"stars":1,"commentCount":3,"comments":[{"id":0,"commenterId":244950080716196890,"content":"\u003cb\u003eWhat steps will reproduce the problem?\u003c/b\u003e\nTry to compile this code with the closure compiler : \r\nvar i \u003d 0; \r\nlab1: do{ \r\n    lab2: do{ \r\n        i++; \r\n        if (1) { \r\n            break lab2; \r\n        } else { \r\n            break lab1; \r\n        } \r\n    } while(false); \r\n} while(false); \r\n\r\nconsole.log(i); \r\n\r\n\u003cb\u003eWhat is the expected output? What do you see instead?\u003c/b\u003e\nThe generated code produced is :\r\nvar a\u003d0;do b:do{a++;break b}while(0);while(0);console.log(a); \r\n\r\nWhich works on all browsers except IE (Looks like IE doesn\u0027t like \r\nthe missing brackets just after the first do instruction).\r\n\r\n\u003cb\u003eWhat version of the product are you using? On what operating system?\u003c/b\u003e\nI am using the version of Jun 16 (latest) on ubuntu 10\r\n\r\n\u003cb\u003ePlease provide any additional information below.\u003c/b\u003e\nStrangely, this bug doesn\u0027t happen when I use PRETTY_PRINT formatting option.","timestamp":1277479250,"attachments":[]},{"id":1,"commenterId":-5060162230523776870,"content":"","timestamp":1277485719,"attachments":[]},{"id":2,"commenterId":-7699928860083865744,"content":"This issue was closed by revision r255.","timestamp":1277510215,"attachments":[]}]}